stagecraft/__init__.py
stagecraft/core/csv.py
stagecraft/core/dataclass.py
stagecraft/core/exceptions.py
stagecraft/core/file.py
stagecraft/core/json.py
stagecraft/core/logging.py
stagecraft/core/os.py
stagecraft/core/pandera.py
stagecraft/core/serializable.py
stagecraft/core/str.py
stagecraft/core/time.py
stagecraft/core/types.py
stagecraft/core/web.py
stagecraft/core/wrappers.py
stagecraft/pipeline/conditions.py
stagecraft/pipeline/context.py
stagecraft/pipeline/data_source.py
stagecraft/pipeline/definition.py
stagecraft/pipeline/descriptors.py
stagecraft/pipeline/descriptors.pyi
stagecraft/pipeline/markers.py
stagecraft/pipeline/memory.py
stagecraft/pipeline/pipeline_metadata.py
stagecraft/pipeline/runner.py
stagecraft/pipeline/schemas.py
stagecraft/pipeline/schemas.pyi
stagecraft/pipeline/stages.py
stagecraft/pipeline/variables.py
stagecraft-0.1.6.dist-info/licenses/LICENSE
stagecraft-0.1.6.dist-info/METADATA
stagecraft-0.1.6.dist-info/WHEEL
stagecraft-0.1.6.dist-info/top_level.txt
stagecraft-0.1.6.dist-info/RECORD
