Metadata-Version: 2.4
Name: stagecraft
Version: 0.1.6
Summary: A Python library for building robust ETL pipelines with declarative stages and data flow management
Author-email: alkndoom <developer@ivent.app>
License: Apache-2.0
Project-URL: Homepage, https://github.com/alkndoom/stagecraft
Project-URL: Documentation, https://github.com/alkndoom/stagecraft#readme
Project-URL: Repository, https://github.com/alkndoom/stagecraft
Project-URL: Issues, https://github.com/alkndoom/stagecraft/issues
Keywords: etl,pipeline,data-processing,workflow,data-engineering
Classifier: Development Status :: 3 - Alpha
Classifier: Intended Audience :: Developers
Classifier: License :: OSI Approved :: Apache Software License
Classifier: Programming Language :: Python :: 3
Classifier: Programming Language :: Python :: 3.10
Classifier: Programming Language :: Python :: 3.11
Classifier: Programming Language :: Python :: 3.12
Classifier: Topic :: Software Development :: Libraries :: Python Modules
Classifier: Topic :: Scientific/Engineering :: Information Analysis
Requires-Python: >=3.10
License-File: LICENSE
Requires-Dist: pandas>=2.0.0
Requires-Dist: numpy>=1.24.0
Requires-Dist: pandera>=0.17.0
Requires-Dist: pyarrow>=11.0.0
Provides-Extra: dev
Requires-Dist: pytest>=7.0.0; extra == "dev"
Requires-Dist: pytest-cov>=4.0.0; extra == "dev"
Requires-Dist: black>=23.0.0; extra == "dev"
Requires-Dist: ruff>=0.1.0; extra == "dev"
Requires-Dist: mypy>=1.0.0; extra == "dev"
Dynamic: license-file
